crimson/formatter/__init__.py
crimson/formatter/templator_patch.py
crimson/formatter/utils.py
crimson_formatter-0.1.0.dist-info/LICENSE
crimson_formatter-0.1.0.dist-info/METADATA
crimson_formatter-0.1.0.dist-info/WHEEL
crimson_formatter-0.1.0.dist-info/top_level.txt
crimson_formatter-0.1.0.dist-info/RECORD
