Metadata-Version: 2.1
Name: crimson-formatter
Version: 0.1.0
Summary: Templator Client. This module is a beta developed without unittest yet.
Author-email: Sisung Kim <sisung.kim1@gmail.com>
Project-URL: Homepage, https://github.com/crimson206/formatter
Project-URL: Bug Tracker, https://github.com/crimson206/formatter/issues
Classifier: Programming Language :: Python :: 3
Classifier: Intended Audience :: Developers
Classifier: Topic :: Software Development :: Build Tools
Classifier: License :: OSI Approved :: MIT License
Classifier: Operating System :: OS Independent
Requires-Python: >=3.9
License-File: LICENSE
Requires-Dist: pydantic
Requires-Dist: crimson-templator
Requires-Dist: pandas
